{"dependencies":[{"name":"./join_us.html","dynamic":true},{"name":"./app.html","dynamic":true},{"name":"./index.html","dynamic":true},{"name":"./m_home.html","dynamic":true},{"name":"./index.js","dynamic":true}],"generated":{"html":"<!DOCTYPE html>\r\n<html lang=\"cn\">\r\n<head>\r\n  <meta charset=\"UTF-8\">\r\n  <meta name=\"viewport\" content=\"width=device-width, initial-scale=1, shrink-to-fit=no\">\r\n  <meta http-equiv=\"X-UA-Compatible\" content=\"ie=edge\">\r\n  <link rel=\"stylesheet\" href=\"https://cdn.bootcss.com/bootstrap/4.0.0/css/bootstrap.min.css\" integrity=\"sha384-Gn5384xqQ1aoWXA+058RXPxPg6fy4IWvTNh0E263XmFcJlSAwiGgFAW/dAiS6JXm\" crossorigin=\"anonymous\">\r\n  <title>众银云测</title>\r\n  <script type=\"text/javascript\">\r\n  if(/Android|webOS|iPhone|iPod|BlackBerry/i.test(navigator.userAgent)) {\r\n     window.location.href = \"./dist/0c2cc9dcc832226ba0e619ac391d7782.html\";\r\n    } else {\r\n      // window.location.href = \"./index.html\";\r\n    }\r\n  </script>\r\n</head>\r\n<body>\r\n  <div id=\"app\">\r\n    <div class=\"navbar\">\r\n      <div class=\"filter\"></div>\r\n      <div class=\"center\">\r\n        <div class=\"logo\">\r\n\r\n        </div>\r\n        <div class=\"right\">\r\n          <li><a href=\"/dist/1acda328dbbee1c02369029f762c9c30.html\">加入我们</a></li>\r\n          <li class=\"m\"><a href=\"/dist/0c2cc9dcc832226ba0e619ac391d7782.html\">众银云测 APP</a></li>\r\n          <li class=\"current\"><a href=\"/dist/index.html\">首页</a></li>\r\n          <li class=\"current\"><a href=\"/dist/bd7a3a6d98109d691ebc78c976a226dc.html\">mobile</a></li>\r\n        </div>\r\n      </div>\r\n    </div>\r\n    <!-- <nav class=\"navbar navbar-expand-lg navbar-dark bg-dark\">\r\n      <a class=\"navbar-brand logo\" href=\"#\"></a>\r\n      <button class=\"navbar-toggler\" type=\"button\" data-toggle=\"collapse\" data-target=\"#navbarNavDropdown\"  aria-expanded=\"false\" aria-label=\"Toggle navigation\">\r\n        <span class=\"navbar-toggler-icon\"></span>\r\n      </button>\r\n\r\n      <div class=\"collapse navbar-collapse \" id=\"navbarNavDropdown\">\r\n        <ul class=\"navbar-nav ml-auto\">\r\n          <li class=\"nav-item active\">\r\n            <a class=\"nav-link\" href=\"./index.html\">首页<span class=\"sr-only\">(current)</span></a>\r\n          </li>\r\n          <li class=\"nav-item\">\r\n            <a class=\"nav-link\" href=\"./app.html\">众银云测 APP</a>\r\n          </li>\r\n          <li class=\"nav-item \">\r\n            <a class=\"nav-link\" href=\"./join_us.html\">加入我们</a>\r\n          </li>\r\n        </ul>\r\n      </div>\r\n    </nav> -->\r\n    <!-- <nav class=\"navbar navbar-expand-lg navbar-light bg-light\">\r\n      <a class=\"navbar-brand\" href=\"#\">Navbar</a>\r\n      <button class=\"navbar-toggler\" type=\"button\" data-toggle=\"collapse\" data-target=\"#navbarNavDropdown\" aria-controls=\"navbarNavDropdown\" aria-expanded=\"false\" aria-label=\"Toggle navigation\">\r\n        <span class=\"navbar-toggler-icon\"></span>\r\n      </button>\r\n      <div class=\"collapse navbar-collapse\" id=\"navbarNavDropdown\">\r\n        <ul class=\"navbar-nav\">\r\n          <li class=\"nav-item active\">\r\n            <a class=\"nav-link\" href=\"#\">Home <span class=\"sr-only\">(current)</span></a>\r\n          </li>\r\n          <li class=\"nav-item\">\r\n            <a class=\"nav-link\" href=\"#\">Features</a>\r\n          </li>\r\n          <li class=\"nav-item\">\r\n            <a class=\"nav-link\" href=\"#\">Pricing</a>\r\n          </li>\r\n          <li class=\"nav-item dropdown\">\r\n            <a class=\"nav-link dropdown-toggle\" href=\"#\" id=\"navbarDropdownMenuLink\" data-toggle=\"dropdown\" aria-haspopup=\"true\" aria-expanded=\"false\">\r\n              Dropdown link\r\n            </a>\r\n            <div class=\"dropdown-menu\" aria-labelledby=\"navbarDropdownMenuLink\">\r\n              <a class=\"dropdown-item\" href=\"#\">Action</a>\r\n              <a class=\"dropdown-item\" href=\"#\">Another action</a>\r\n              <a class=\"dropdown-item\" href=\"#\">Something else here</a>\r\n            </div>\r\n          </li>\r\n        </ul>\r\n      </div>\r\n    </nav> -->\r\n    <div class=\"header\">\r\n     <div class=\"main\">\r\n       <p>众银云测，是一家专注于泛金融领域的信息技术公司，致力深耕人工智能与区块链技术</p>\r\n       <div class=\"more\">\r\n         <div onclick=\"window.scroll(0, 1200)\">了解详情</div>\r\n         <div class=\"custom-service\" onclick=\"window.scroll(0, 1500)\">咨询客服</div>\r\n       </div>\r\n       <div class=\"arrow-bottom\" onclick=\"window.scroll(0, 1200)\">\r\n\r\n      </div>\r\n     </div>\r\n   </div>\r\n   <div class=\"product\">\r\n     <h1 class=\"product-title\">我们的产品</h1>\r\n     <div class=\"product-body\">\r\n        <div>\r\n          <h2>众银云测APP-最好用的贷款助手</h2>\r\n          <p>众银云测APP，是基于iOS/andriod双平台开发的贷款助手APP，\r\n          为深圳市众银云测信息技术有限公司自主打造的贷款信息分享平台，致\r\n          力于分享优质贷款产品，连接客户与产品方，并通过智能匹配引擎助力\r\n          共享销售，为客户提供专业高效的服务，为产品方获取精准客户。</p>\r\n        </div>\r\n     </div>\r\n   </div>\r\n   <div class=\"footer\">\r\n       <div class=\"center\">\r\n         <div class=\"logo\">\r\n\r\n         </div>\r\n         <div class=\"info\">\r\n           <div>\r\n             <span>客服电话：0755-21046730</span>\r\n             <span class=\"email\">邮箱：zyyc@ibankmatch.com</span>\r\n           </div>\r\n           <div class=\"address\">\r\n             公司地址：&nbsp;&nbsp;深圳市龙华新区大浪街道龙峰三路锦华大厦&nbsp;&nbsp;2506&nbsp;&nbsp;室\r\n           </div>\r\n         </div>\r\n         <div class=\"copyright\">\r\n           深圳市众银云测信息技术有限公司&nbsp;&nbsp;&nbsp;&nbsp;Copyright 2018&nbsp;&nbsp;&nbsp;&nbsp;www.ibankmatch.com&nbsp;&nbsp;粤ICP备18015540号-1\r\n         </div>\r\n       </div>\r\n   </div>\r\n  </div>\r\n  <script src=\"https://cdn.bootcss.com/jquery/3.2.1/jquery.slim.min.js\" integrity=\"sha384-KJ3o2DKtIkvYIK3UENzmM7KCkRr/rE9/Qpg6aAZGJwFDMVNA/GpGFF93hXpG5KkN\" crossorigin=\"anonymous\"></script>\r\n  <script src=\"https://cdn.bootcss.com/popper.js/1.12.9/umd/popper.min.js\" integrity=\"sha384-ApNbgh9B+Y1QKtv3Rn7W3mgPxhU9K/ScQsAP7hUibX39j7fakFPskvXusvfa0b4Q\" crossorigin=\"anonymous\"></script>\r\n  <script src=\"https://cdn.bootcss.com/bootstrap/4.0.0/js/bootstrap.min.js\" integrity=\"sha384-JZR6Spejh4U02d8jOt6vLEHfe/JQGiRRSQQxSfFWpi1MquVdAyjUar5+76PVCmYl\" crossorigin=\"anonymous\"></script>\r\n  <script src=\"/dist/bank-match.js\" charset=\"utf-8\"></script>\r\n</body>\r\n</html>\r\n"},"hash":"873279f5a3c41b46d3539ae83e435fc1","cacheData":{}}